superconfig/__init__.py
superconfig/superconfig.py
superconfig-1.0.0.dist-info/METADATA
superconfig-1.0.0.dist-info/RECORD
superconfig-1.0.0.dist-info/WHEEL
superconfig-1.0.0.dist-info/top_level.txt
