Metadata-Version: 2.1
Name: superconfig
Version: 1.0.0
Summary: Simple & powerful python script configuration
Home-page: https://github.com/ondrejsika/python-superconfig
Author: Ondrej Sika
Author-email: ondrej@ondrejsika.com
License: UNKNOWN
Platform: UNKNOWN
